containerd/__init__.py
containerd/events/__init__.py
containerd/events/container_pb2.py
containerd/events/container_pb2_grpc.py
containerd/events/content_pb2.py
containerd/events/content_pb2_grpc.py
containerd/events/image_pb2.py
containerd/events/image_pb2_grpc.py
containerd/events/namespace_pb2.py
containerd/events/namespace_pb2_grpc.py
containerd/events/snapshot_pb2.py
containerd/events/snapshot_pb2_grpc.py
containerd/events/task_pb2.py
containerd/events/task_pb2_grpc.py
containerd/protobuf/__init__.py
containerd/protobuf/plugin/__init__.py
containerd/protobuf/plugin/fieldpath_pb2.py
containerd/protobuf/plugin/fieldpath_pb2_grpc.py
containerd/services/__init__.py
containerd/services/containers/__init__.py
containerd/services/containers/v1/__init__.py
containerd/services/containers/v1/containers_pb2.py
containerd/services/containers/v1/containers_pb2_grpc.py
containerd/services/content/__init__.py
containerd/services/content/v1/__init__.py
containerd/services/content/v1/content_pb2.py
containerd/services/content/v1/content_pb2_grpc.py
containerd/services/diff/__init__.py
containerd/services/diff/v1/__init__.py
containerd/services/diff/v1/diff_pb2.py
containerd/services/diff/v1/diff_pb2_grpc.py
containerd/services/events/__init__.py
containerd/services/events/v1/__init__.py
containerd/services/events/v1/events_pb2.py
containerd/services/events/v1/events_pb2_grpc.py
containerd/services/images/__init__.py
containerd/services/images/v1/__init__.py
containerd/services/images/v1/images_pb2.py
containerd/services/images/v1/images_pb2_grpc.py
containerd/services/introspection/__init__.py
containerd/services/introspection/v1/__init__.py
containerd/services/introspection/v1/introspection_pb2.py
containerd/services/introspection/v1/introspection_pb2_grpc.py
containerd/services/leases/__init__.py
containerd/services/leases/v1/__init__.py
containerd/services/leases/v1/leases_pb2.py
containerd/services/leases/v1/leases_pb2_grpc.py
containerd/services/namespaces/__init__.py
containerd-1.5.3.dist-info/METADATA
containerd-1.5.3.dist-info/WHEEL
containerd-1.5.3.dist-info/top_level.txt
containerd-1.5.3.dist-info/RECORD
