Metadata-Version: 2.1
Name: containerd
Version: 1.5.3
Summary: containerd API for Python
Home-page: https://github.com/siemens/pycontainerd
Author: Silvano Cirujano Cuesta
Author-email: silvano.cirujano-cuesta@siemens.com
License: Apache-2.0
Platform: UNKNOWN
Classifier: Development Status :: 4 - Beta
Classifier: Operating System :: POSIX :: Linux
Classifier: Programming Language :: Python :: 3.6
Classifier: Programming Language :: Python :: 3 :: Only
Classifier: License :: OSI Approved :: Apache Software License
Classifier: Topic :: Software Development :: Libraries
Classifier: Topic :: System :: Clustering
Classifier: Topic :: Utilities
Requires-Dist: grpcio
Requires-Dist: protobuf (>=3.13.0)
